analyze_log.py
cli.py
locale_export_template.py
locale_validate.py
manifest_diff.py
restore_from_manifest.py
cfc/__init__.py
cfc/controller.py
cfc/detectors.py
cfc/gui.py
cfc/manifest.py
cfc/py.typed
cfc/locales/en.json
cfc/locales/ku.json
cfc/locales/tr.json
cfc_corrupted_file_cleaner-0.1.2.dist-info/licenses/LICENSE
cfc_corrupted_file_cleaner-0.1.2.dist-info/METADATA
cfc_corrupted_file_cleaner-0.1.2.dist-info/WHEEL
cfc_corrupted_file_cleaner-0.1.2.dist-info/entry_points.txt
cfc_corrupted_file_cleaner-0.1.2.dist-info/top_level.txt
cfc_corrupted_file_cleaner-0.1.2.dist-info/RECORD
