Metadata-Version: 2.4
Name: cfc-corrupted-file-cleaner
Version: 0.1.2
Summary: Corrupted File Cleaner: scan, preview, quarantine, and manage potentially corrupted or encrypted files.
Author: Your Name
License-Expression: MIT
Project-URL: Homepage, https://example.com/cfc
Project-URL: Documentation, https://example.com/cfc/docs
Project-URL: Source, https://example.com/cfc/source
Project-URL: Issues, https://example.com/cfc/issues
Keywords: corruption,scanner,files,hash,quarantine,forensics,forensic,security,integrity
Classifier: Development Status :: 3 - Alpha
Classifier: Intended Audience :: End Users/Desktop
Classifier: Intended Audience :: System Administrators
Classifier: Topic :: Utilities
Classifier: Topic :: Security
Classifier: Programming Language :: Python :: 3
Classifier: Programming Language :: Python :: 3.10
Classifier: Programming Language :: Python :: 3.11
Classifier: Programming Language :: Python :: 3.12
Classifier: Operating System :: OS Independent
Requires-Python: >=3.10
License-File: LICENSE
Requires-Dist: customtkinter
Requires-Dist: Pillow
Requires-Dist: send2trash
Requires-Dist: pikepdf
Requires-Dist: mutagen
Provides-Extra: cli
Provides-Extra: dev
Requires-Dist: build; extra == "dev"
Requires-Dist: twine; extra == "dev"
Requires-Dist: pytest; extra == "dev"
Requires-Dist: typing-extensions; extra == "dev"
Dynamic: license-file
